carconnectivity_connector_volkswagen_na-0.1.5.dist-info/licenses/LICENSE
carconnectivity_connectors/volkswagen_na/__init__.py
carconnectivity_connectors/volkswagen_na/_version.py
carconnectivity_connectors/volkswagen_na/capability.py
carconnectivity_connectors/volkswagen_na/charging.py
carconnectivity_connectors/volkswagen_na/climatization.py
carconnectivity_connectors/volkswagen_na/command_impl.py
carconnectivity_connectors/volkswagen_na/connector.py
carconnectivity_connectors/volkswagen_na/vehicle.py
carconnectivity_connectors/volkswagen_na/auth/__init__.py
carconnectivity_connectors/volkswagen_na/auth/auth_util.py
carconnectivity_connectors/volkswagen_na/auth/myvw_session.py
carconnectivity_connectors/volkswagen_na/auth/openid_session.py
carconnectivity_connectors/volkswagen_na/auth/session_manager.py
carconnectivity_connectors/volkswagen_na/auth/vw_web_session.py
carconnectivity_connectors/volkswagen_na/auth/helpers/blacklist_retry.py
carconnectivity_connectors/volkswagen_na/ui/connector_ui.py
carconnectivity_connector_volkswagen_na-0.1.5.dist-info/METADATA
carconnectivity_connector_volkswagen_na-0.1.5.dist-info/WHEEL
carconnectivity_connector_volkswagen_na-0.1.5.dist-info/top_level.txt
carconnectivity_connector_volkswagen_na-0.1.5.dist-info/RECORD
