Metadata-Version: 2.4
Name: carconnectivity-connector-volkswagen-na
Version: 0.1.5
Summary: CarConnectivity connector for Volkswagen NA services
Author: Till Steinbach, Zack Cornelius
License: MIT License
Classifier: Development Status :: 3 - Alpha
Classifier: License :: OSI Approved :: MIT License
Classifier: Intended Audience :: Developers
Classifier: Programming Language :: Python :: 3.9
Classifier: Programming Language :: Python :: 3.10
Classifier: Programming Language :: Python :: 3.11
Classifier: Programming Language :: Python :: 3.12
Classifier: Programming Language :: Python :: 3.13
Classifier: Topic :: Software Development :: Libraries
Requires-Python: >=3.9
License-File: LICENSE
Requires-Dist: carconnectivity>=0.11
Requires-Dist: oauthlib~=3.3.1
Requires-Dist: requests~=2.32.3
Requires-Dist: pyjwt~=2.10
Requires-Dist: pkce~=1.0.3
Dynamic: license-file
